versioning_util/tests/__init__.py
versioning_util/versioning_util/__init__.py
versioning_util/versioning_util/versioning.py
versioning_util-0.1.0.dist-info/METADATA
versioning_util-0.1.0.dist-info/WHEEL
versioning_util-0.1.0.dist-info/RECORD
