Metadata-Version: 2.1
Name: versioning-util
Version: 0.1.0
Summary: 
Author: imnublet
Author-email: sayfgmaul@gmail.com
Requires-Python: >=3.10,<4.0
Classifier: Programming Language :: Python :: 3
Classifier: Programming Language :: Python :: 3.10
Classifier: Programming Language :: Python :: 3.11
Classifier: Programming Language :: Python :: 3.12
Requires-Dist: importlib-resources (>=6.4.0,<7.0.0)
